linien_client/__init__.py
linien_client/connection.py
linien_client/deploy.py
linien_client/device.py
linien_client/exceptions.py
linien_client/remote_parameters.py
linien_client-2.1.0.dist-info/METADATA
linien_client-2.1.0.dist-info/WHEEL
linien_client-2.1.0.dist-info/top_level.txt
linien_client-2.1.0.dist-info/RECORD
