Metadata-Version: 2.1
Name: linien-client
Version: 2.1.0
Summary: Client components of the Linien spectroscopy lock application.
Author-email: Benjamin Wiegand <benjamin.wiegand@physik.hu-berlin.de>, Bastian Leykauf <leykauf@physik.hu-berlin.de>, Robert Jördens <rj@quartiq.de>, Christian Freier <christian.freier@gmail.com>, Doron Behar <doron.behar@gmail.com>
Maintainer-email: Bastian Leykauf <leykauf@physik.hu-berlin.de>
Project-URL: Homepage, https://github.com/linien-org/linien/
Classifier: Programming Language :: Python :: 3
Classifier: License :: OSI Approved :: GNU General Public License v3 (GPLv3)
Classifier: Operating System :: OS Independent
Requires-Python: >=3.8
Requires-Dist: fabric <4.0,>=3.2.2
Requires-Dist: typing-extensions <5.0,>=4.5.0
Requires-Dist: linien-common ==2.1.0
